pprintex/__init__.py
pprintex/pp_new.py
printex-0.0.7.dist-info/LICENSE.txt
printex-0.0.7.dist-info/METADATA
printex-0.0.7.dist-info/WHEEL
printex-0.0.7.dist-info/top_level.txt
printex-0.0.7.dist-info/RECORD
