Metadata-Version: 2.1
Name: printex
Version: 0.0.7
Summary: similar to pprint, but shows all object field values.
Home-page: https://github.com/MoserMichael/pprintex
Author: Michael Moser
Author-email: moser.michael@gmail.com
License: MIT
Project-URL: Bug Tracker, https://github.com/MoserMichael/pprintex/issues
Keywords: debugging,tracing,pretty printing
Platform: UNKNOWN
Classifier: Programming Language :: Python :: 3
Classifier: License :: OSI Approved :: MIT License
Classifier: Operating System :: OS Independent
Classifier: Intended Audience :: Developers
Classifier: Programming Language :: Python :: 3
Classifier: Topic :: Software Development :: Testing
Classifier: Topic :: Software Development :: Libraries
Classifier: Topic :: System :: Logging
Classifier: Topic :: Utilities
Requires-Python: >=3.3
